wafflesbot/__init__.py
wafflesbot/__version__.py
wafflesbot/jmap.py
wafflesbot/logging.py
wafflesbot/main.py
wafflesbot/py.typed
wafflesbot/reply.py
wafflesbot/waffles.py
wafflesbot-0.1.21.dist-info/LICENSE
wafflesbot-0.1.21.dist-info/METADATA
wafflesbot-0.1.21.dist-info/WHEEL
wafflesbot-0.1.21.dist-info/entry_points.txt
wafflesbot-0.1.21.dist-info/RECORD
