Metadata-Version: 2.3
Name: wafflesbot
Version: 0.1.21
Summary: Tech recruiter auto reply bot using JMAP
License: GPL-3.0-or-later
Author: Stephen Kent
Author-email: smkent@smkent.net
Requires-Python: >=3.9,<4.0
Classifier: Development Status :: 3 - Alpha
Classifier: Operating System :: OS Independent
Classifier: Topic :: Communications :: Email :: Post-Office
Classifier: Topic :: Office/Business :: Groupware
Classifier: Topic :: Software Development :: Libraries :: Python Modules
Classifier: Typing :: Typed
Requires-Dist: jmapc (>=0.2.0)
Requires-Dist: replyowl (>=0.1.0)
